bitutils/__init__.py
bitutils/base.py
bitutils/hash.py
bitutils/objects.py
bitutils/utils.py
bitutils-0.1.2.dist-info/DESCRIPTION.rst
bitutils-0.1.2.dist-info/METADATA
bitutils-0.1.2.dist-info/RECORD
bitutils-0.1.2.dist-info/WHEEL
bitutils-0.1.2.dist-info/metadata.json
bitutils-0.1.2.dist-info/top_level.txt
